crispy_formset_modal/__init__.py
crispy_formset_modal/configs.py
crispy_formset_modal/helper.py
crispy_formset_modal/layout.py
crispy_formset_modal/locale/es/LC_MESSAGES/django.mo
crispy_formset_modal/locale/es/LC_MESSAGES/django.po
crispy_formset_modal/locale/es/LC_MESSAGES/djangojs.mo
crispy_formset_modal/locale/es/LC_MESSAGES/djangojs.po
crispy_formset_modal/static/crispy_formset_modal/js/crispy-formset-modal.min.js
crispy_formset_modal/static/crispy_formset_modal/js/crispy-formset-modal.min.js.map
crispy_formset_modal/templates/crispy_formset_modal/bootstrap4/edit_button.html
crispy_formset_modal/templates/crispy_formset_modal/bootstrap4/empty_state.html
crispy_formset_modal/templates/crispy_formset_modal/bootstrap4/form.html
crispy_formset_modal/templates/crispy_formset_modal/bootstrap4/modal.html
crispy_formset_modal/templates/crispy_formset_modal/bootstrap4/table.html
crispy_formset_modal/templates/crispy_formset_modal/bootstrap5/edit_button.html
crispy_formset_modal/templates/crispy_formset_modal/bootstrap5/empty_state.html
crispy_formset_modal/templates/crispy_formset_modal/bootstrap5/form.html
crispy_formset_modal/templates/crispy_formset_modal/bootstrap5/modal.html
crispy_formset_modal/templates/crispy_formset_modal/bootstrap5/table.html
crispy_formset_modal/templates/crispy_formset_modal/bulma/edit_button.html
crispy_formset_modal/templates/crispy_formset_modal/bulma/empty_state.html
crispy_formset_modal/templates/crispy_formset_modal/bulma/form.html
crispy_formset_modal/templates/crispy_formset_modal/bulma/modal.html
crispy_formset_modal/templates/crispy_formset_modal/bulma/table.html
crispy_formset_modal/templates/crispy_formset_modal/tailwind/edit_button.html
crispy_formset_modal/templates/crispy_formset_modal/tailwind/empty_state.html
crispy_formset_modal/templates/crispy_formset_modal/tailwind/form.html
crispy_formset_modal/templates/crispy_formset_modal/tailwind/modal.html
crispy_formset_modal/templates/crispy_formset_modal/tailwind/table.html
django_crispy_formset_modal-0.15.dist-info/licenses/LICENSE
django_crispy_formset_modal-0.15.dist-info/METADATA
django_crispy_formset_modal-0.15.dist-info/WHEEL
django_crispy_formset_modal-0.15.dist-info/top_level.txt
django_crispy_formset_modal-0.15.dist-info/RECORD
