Metadata-Version: 2.4
Name: django-crispy-formset-modal
Version: 0.15
Summary: Django app that provides an easy way to manage and manipulate formsets using modals with Django Crispy Forms.
Author-email: Blas Isaias Fernández Cáceres <blasferna@gmail.com>
Project-URL: homepage, https://blasferna.github.io/django-crispy-formset-modal
Project-URL: bugs, https://github.com/blasferna/django-crispy-formset-modal/issues
Classifier: Development Status :: 5 - Production/Stable
Classifier: Framework :: Django
Classifier: Framework :: Django :: 3.2
Classifier: Framework :: Django :: 4.0
Classifier: Framework :: Django :: 4.1
Classifier: Framework :: Django :: 4.2
Classifier: Framework :: Django :: 5.1
Classifier: Framework :: Django :: 5.2
Classifier: Intended Audience :: Developers
Classifier: Natural Language :: English
Classifier: Topic :: Software Development :: Libraries
Classifier: Topic :: Software Development :: Libraries :: Python Modules
Classifier: Programming Language :: Python
Classifier: Programming Language :: Python :: 3.7
Classifier: Programming Language :: Python :: 3.8
Classifier: Programming Language :: Python :: 3.9
Classifier: Programming Language :: Python :: 3.10
Classifier: Programming Language :: Python :: 3.11
Classifier: Programming Language :: Python :: 3.12
Classifier: Programming Language :: Python :: 3.13
Requires-Python: >=3.7
License-File: LICENSE
Requires-Dist: Django>=3.2
Requires-Dist: django-crispy-forms>=1.13.0
Requires-Dist: django-extra-views>=0.14.0
Dynamic: license-file
